polymeasure/__init__.py
polymeasure/core.py
polymeasure/core_experiment.py
polymeasure/standard.py
polymeasure-0.1.8.dist-info/LICENSE
polymeasure-0.1.8.dist-info/METADATA
polymeasure-0.1.8.dist-info/WHEEL
polymeasure-0.1.8.dist-info/top_level.txt
polymeasure-0.1.8.dist-info/RECORD
