Metadata-Version: 2.1
Name: polymeasure
Version: 0.1.8
Summary: A python analysis package for SQL data modelling.
Author-email: Josh Grant <jagmanjg@gmail.com>
Project-URL: Homepage, https://github.com/jgrant-the-giant/polymeasure
Project-URL: Bug Tracker, https://github.com/jgrant-the-giant/polymeasure/issues
Classifier: Programming Language :: Python :: 3
Classifier: License :: OSI Approved :: MIT License
Classifier: Operating System :: OS Independent
Requires-Python: >=3.7
License-File: LICENSE
